setup.py
gbdx_interactive/__init__.py
gbdx_interactive/gbdx_interactive.py
gbdx_interactive.egg-info/PKG-INFO
gbdx_interactive.egg-info/SOURCES.txt
gbdx_interactive.egg-info/dependency_links.txt
gbdx_interactive.egg-info/not-zip-safe
gbdx_interactive.egg-info/requires.txt
gbdx_interactive.egg-info/top_level.txt