Metadata-Version: 1.0
Name: gbdx-interactive
Version: 0.0.1
Summary: gbdxtools, but interactive.
Home-page: https://github.com/nricklin/gbdx-interactive
Author: Nate Ricklin
Author-email: nate.ricklin@digitalglobe.com
License: MIT
Platform: UNKNOWN
